oslui/__init__.py
oslui/main.py
oslui/utils.py
oslui/agent/__init__.py
oslui/agent/base.py
oslui/agent/chat.py
oslui/agent/query.py
oslui/agent/translate.py
oslui/command/__init__.py
oslui/command/base.py
oslui/command/language_command.py
oslui/command/shell_command.py
oslui/memory/__init__.py
oslui/memory/base.py
oslui/prompts/__init__.py
oslui/prompts/chat.py
oslui/prompts/query.py
oslui/prompts/translate.py
oslui/query/__init__.py
oslui-0.1.0.dist-info/LICENSE
oslui-0.1.0.dist-info/METADATA
oslui-0.1.0.dist-info/WHEEL
oslui-0.1.0.dist-info/entry_points.txt
oslui-0.1.0.dist-info/top_level.txt
oslui-0.1.0.dist-info/RECORD
